comment
comment.py
setup.cfg
setup.py
comment_builder.egg-info/PKG-INFO
comment_builder.egg-info/SOURCES.txt
comment_builder.egg-info/dependency_links.txt
comment_builder.egg-info/top_level.txt