Metadata-Version: 1.0
Name: comment-builder
Version: 0.1
Summary: A python script for displaying aligned comments
Home-page: https://github.com/adamatan/comment-builder
Author: Adam Matan
Author-email: adam@matan.name
License: MIT
Platform: UNKNOWN
